popupdict/__init__.py
popupdict/main.py
popupdict/config/__init__.py
popupdict/config/configuration.py
popupdict/config/default.ini
popupdict/config/exception.py
popupdict/config/query/__init__.py
popupdict/config/query/base.py
popupdict/config/query/youdao_zhiyun.py
popupdict/config/speech/__init__.py
popupdict/config/speech/base.py
popupdict/daemon/__init__.py
popupdict/daemon/query.py
popupdict/gtk/__init__.py
popupdict/query/__init__.py
popupdict/query/adapter.py
popupdict/query/cache.py
popupdict/query/result.py
popupdict/query/client/__init__.py
popupdict/query/client/abstract.py
popupdict/query/client/fake.py
popupdict/query/client/youdao_web.py
popupdict/query/client/youdao_zhiyun.py
popupdict/speech/__init__.py
popupdict/speech/adapter.py
popupdict/speech/client/__init__.py
popupdict/speech/client/abstract.py
popupdict/speech/client/youdao.py
popupdict/ui/__init__.py
popupdict/ui/popup.py
popupdict/ui/widgets.py
popupdict/util/__init__.py
popupdict/util/dir.py
popupdict/util/logging.py
popupdict/util/selection.py
popupdict/util/selection_filter.py
popupdict-0.3.3.dist-info/LICENSE
popupdict-0.3.3.dist-info/METADATA
popupdict-0.3.3.dist-info/WHEEL
popupdict-0.3.3.dist-info/entry_points.txt
popupdict-0.3.3.dist-info/top_level.txt
popupdict-0.3.3.dist-info/zip-safe
popupdict-0.3.3.dist-info/RECORD
