Metadata-Version: 2.1
Name: popupdict
Version: 0.3.3
Summary: Linux 下的划词翻译工具，支持有道智云等多种翻译服务
Home-page: https://github.com/bianjp/popup-dict
Author: Bian Jiaping
Author-email: ssbianjp@gmail.com
License: MIT
Keywords: dict youdao
Platform: Linux
Classifier: Development Status :: 3 - Alpha
Classifier: Environment :: X11 Applications :: GTK
Classifier: Operating System :: POSIX :: Linux
Classifier: License :: OSI Approved :: MIT License
Classifier: Intended Audience :: End Users/Desktop
Classifier: Natural Language :: Chinese (Simplified)
Classifier: Programming Language :: Python :: 3 :: Only
Classifier: Programming Language :: Python :: 3.6
Classifier: Programming Language :: Python :: 3.7
Classifier: Topic :: Desktop Environment
Classifier: Topic :: Education
Requires-Python: >= 3.6
Requires-Dist: psutil
Requires-Dist: requests
